zsm/__init__.py
zsm/cli.py
zsm/config.py
zsm/logging.py
zsm/manage.py
zsm/zfs.py
zsm-0.4.0.dist-info/LICENSE
zsm-0.4.0.dist-info/METADATA
zsm-0.4.0.dist-info/WHEEL
zsm-0.4.0.dist-info/entry_points.txt
zsm-0.4.0.dist-info/top_level.txt
zsm-0.4.0.dist-info/RECORD
