Metadata-Version: 2.1
Name: zsm
Version: 0.4.0
Summary: ZFS Snapshot Manager
Home-page: UNKNOWN
Author: Mattias Lindvall
Author-email: mattias.lindvall@gmail.com
License: BSD-2-Clause
Project-URL: Documentation, https://zsm.readthedocs.io/
Project-URL: Source, https://github.com/thnee/zsm
Keywords: zfs snapshots freebsd linux
Platform: UNKNOWN
Classifier: Development Status :: 4 - Beta
Classifier: Environment :: Console
Classifier: Intended Audience :: System Administrators
Classifier: Operating System :: POSIX :: BSD :: FreeBSD
Classifier: Operating System :: POSIX :: Linux
Classifier: Programming Language :: Python
Classifier: Programming Language :: Python :: 3
Classifier: Programming Language :: Python :: 3.7
Classifier: Programming Language :: Python :: 3.8
Classifier: Programming Language :: Python :: 3.9
Classifier: Programming Language :: Python :: 3.10
Classifier: Programming Language :: Python :: 3 :: Only
Classifier: Topic :: System :: Filesystems
Requires-Python: >=3.7
License-File: LICENSE
Requires-Dist: click (~=8.0.1)
Requires-Dist: pid (~=3.0.4)
Requires-Dist: pyyaml (~=5.4.1)
Requires-Dist: marshmallow (~=3.13.0)
Provides-Extra: build
Requires-Dist: wheel (~=0.37.1) ; extra == 'build'
Requires-Dist: twine (~=3.8.0) ; extra == 'build'
Provides-Extra: test
Requires-Dist: pytest (~=7.0.1) ; extra == 'test'
Requires-Dist: pytest-cov (~=3.0.0) ; extra == 'test'
Requires-Dist: flake8 (~=4.0.1) ; extra == 'test'
Requires-Dist: flake8-bugbear (~=22.1.11) ; extra == 'test'
Requires-Dist: black (~=22.1.0) ; extra == 'test'
Requires-Dist: isort (~=5.10.1) ; extra == 'test'
Requires-Dist: invoke (~=1.6.0) ; extra == 'test'
Requires-Dist: tox (~=3.24.5) ; extra == 'test'
Requires-Dist: freezegun (~=1.2.0) ; extra == 'test'
